django_zerodowntime-0.3.0.dist-info/DESCRIPTION.rst
django_zerodowntime-0.3.0.dist-info/METADATA
django_zerodowntime-0.3.0.dist-info/RECORD
django_zerodowntime-0.3.0.dist-info/WHEEL
django_zerodowntime-0.3.0.dist-info/metadata.json
django_zerodowntime-0.3.0.dist-info/top_level.txt
zerodowntime/__init__.py
zerodowntime/migration_utils.py
zerodowntime/models.py
zerodowntime/management/__init__.py
zerodowntime/management/commands/__init__.py
zerodowntime/management/commands/check_migrations.py
zerodowntime/management/commands/install_git_hooks.py
