Metadata-Version: 2.0
Name: django-zerodowntime
Version: 0.3.0
Summary: A Django Migrations extension providing a framework for Zero Downtime Continuous Delivery.
Home-page: https://github.com/rentlytics/django-zerodowntime
Author: Phil Plante
Author-email: phil@rentlytics.com
License: MIT
Platform: UNKNOWN
Classifier: Development Status :: 2 - Pre-Alpha
Classifier: Environment :: Web Environment
Classifier: Framework :: Django
Classifier: Intended Audience :: Developers
Classifier: License :: OSI Approved :: MIT License
Classifier: Operating System :: OS Independent
Classifier: Programming Language :: Python
Classifier: Programming Language :: Python :: 2.7
Classifier: Programming Language :: Python :: 3.5
Classifier: Topic :: Internet :: WWW/HTTP
Requires-Dist: django (>=1.8)
Requires-Dist: invoke (==0.13.0)
